LICENSE
README.md
setup.py
catrix/Environment.py
catrix/__init__.py
catrix/buddha.py
catrix/cat.py
catrix/chatdata.py
catrix.egg-info/PKG-INFO
catrix.egg-info/SOURCES.txt
catrix.egg-info/dependency_links.txt
catrix.egg-info/requires.txt
catrix.egg-info/top_level.txt