Metadata-Version: 2.1
Name: catrix
Version: 1.0.0
Summary: A virtual realm simulation of mindful and exploring cats.
Home-page: https://github.com/ishanoshada/Catrix
Author: Ishan Oshada
Author-email: ic31908@gmail.com
License: UNKNOWN
Keywords: virtual realm simulation cats mindful exploring
Platform: UNKNOWN
Classifier: Development Status :: 5 - Production/Stable
Classifier: Intended Audience :: Developers
Classifier: License :: OSI Approved :: MIT License
Classifier: Programming Language :: Python :: 3
Classifier: Programming Language :: Python :: 3.7
Classifier: Programming Language :: Python :: 3.8
Classifier: Programming Language :: Python :: 3.9
Classifier: Programming Language :: Python :: 3.10
Classifier: Topic :: Software Development :: Libraries :: Python Modules
